LICENSE
MANIFEST.in
README.rst
setup.py
django_image_helper.egg-info/PKG-INFO
django_image_helper.egg-info/SOURCES.txt
django_image_helper.egg-info/dependency_links.txt
django_image_helper.egg-info/not-zip-safe
django_image_helper.egg-info/requires.txt
django_image_helper.egg-info/top_level.txt
example/sample/__init__.py
example/sample/admin.py
example/sample/models.py
example/sample/views.py
example/sample/migrations/0001_initial.py
example/sample/migrations/__init__.py
image_helper/__init__.py
image_helper/fields.py
image_helper/widgets.py
image_helper/tests/__init__.py
image_helper/tests/test_fields.py
image_helper/tests/test_app/__init__.py
image_helper/tests/test_app/apps.py
image_helper/tests/test_app/models.py
image_helper/tests/test_app/migrations/0001_initial.py
image_helper/tests/test_app/migrations/__init__.py
requirements/requirements.txt
requirements/test.txt